ebenezer/__init__.py
ebenezer/py.typed
ebenezer/commands/__init__.py
ebenezer/commands/app.py
ebenezer/commands/backlight.py
ebenezer/commands/helpers.py
ebenezer/commands/keyboard.py
ebenezer/commands/ui.py
ebenezer/commands/volume.py
ebenezer/commands/wallpaper.py
ebenezer/config/__init__.py
ebenezer/config/applications.py
ebenezer/config/bar.py
ebenezer/config/colors.py
ebenezer/config/environment.py
ebenezer/config/fonts.py
ebenezer/config/keybindings.py
ebenezer/config/loader.py
ebenezer/config/lock_screen.py
ebenezer/config/monitoring.py
ebenezer/config/scratchpads.py
ebenezer/config/settings.py
ebenezer/core/__init__.py
ebenezer/core/command.py
ebenezer/core/dict.py
ebenezer/core/files.py
ebenezer/core/groups.py
ebenezer/core/keys.py
ebenezer/core/layout.py
ebenezer/core/notify.py
ebenezer/core/requests.py
ebenezer/core/screen.py
ebenezer/core/startup.py
ebenezer/core/theme.py
ebenezer/core/wallpaper.py
ebenezer/core/yaml.py
ebenezer/rofi/__init__.py
ebenezer/rofi/_vars.template.rasi
ebenezer/rofi/launcher.rasi
ebenezer/rofi/modals/__init__.py
ebenezer/rofi/modals/confirm.py
ebenezer/rofi/modals/confirm.rasi
ebenezer/rofi/powermenu/__init__.py
ebenezer/rofi/powermenu/main.py
ebenezer/rofi/powermenu/powermenu.rasi
ebenezer/rofi/settings/__init__.py
ebenezer/rofi/settings/main.py
ebenezer/rofi/settings/theme.rasi
ebenezer/rofi/settings/wallpaper_menu.sh
ebenezer/rofi/wallpaper_menu/__init__.py
ebenezer/rofi/wallpaper_menu/main.py
ebenezer/rofi/wallpaper_menu/theme.rasi
ebenezer/rofi/wallpaper_menu/wallpaper_menu.sh
ebenezer/ui/__init__.py
ebenezer/ui/lock_screen.py
ebenezer/ui/settings/__init__.py
ebenezer/ui/settings/about_frame.py
ebenezer/ui/settings/appearance_frame.py
ebenezer/ui/settings/environment_frame.py
ebenezer/ui/settings/helpers.py
ebenezer/ui/settings/main.py
ebenezer/ui/settings/styles.py
ebenezer/ui/settings/wallpaper_frame.py
ebenezer/ui/settings/widgets/__init__.py
ebenezer/ui/settings/widgets/field.py
ebenezer/ui/settings/widgets/label.py
qtile_ebenezer-0.1.36.dist-info/licenses/LICENSE
qtile_ebenezer-0.1.36.dist-info/METADATA
qtile_ebenezer-0.1.36.dist-info/WHEEL
qtile_ebenezer-0.1.36.dist-info/entry_points.txt
qtile_ebenezer-0.1.36.dist-info/top_level.txt
qtile_ebenezer-0.1.36.dist-info/RECORD
