Metadata-Version: 2.4
Name: qtile-ebenezer
Version: 0.1.36
Summary: This repository provides a collection of widgets and behaviors spanning Desktop to Qtile Tiling Window Manager.
Home-page: https://github.com/williampsena/qtile-ebenezer
Author: William Sena
Author-email: me@willsena.dev
Classifier: Programming Language :: Python :: 3
Classifier: License :: OSI Approved :: MIT License
Classifier: Operating System :: OS Independent
Requires-Python: >=3.10
License-File: LICENSE
Requires-Dist: requests>=2.32.3
Requires-Dist: qtile>=0.30.0
Requires-Dist: pillow>=11.1.0
Requires-Dist: psutil>=6.2.0
Requires-Dist: ruamel.yaml>=0.17.0
Requires-Dist: cairocffi>=1.7.1
Requires-Dist: click>=8.0.0
Requires-Dist: colorama>=0.4.6
Dynamic: author
Dynamic: author-email
Dynamic: classifier
Dynamic: description
Dynamic: description-content-type
Dynamic: home-page
Dynamic: license-file
Dynamic: requires-dist
Dynamic: requires-python
Dynamic: summary
